pg_db_tools/__init__.py
pg_db_tools/dot_renderer.py
pg_db_tools/graph.py
pg_db_tools/md_renderer.py
pg_db_tools/modification.py
pg_db_tools/object_filter.py
pg_db_tools/pg_types.py
pg_db_tools/rst_renderer.py
pg_db_tools/spec.schema
pg_db_tools/sql_renderer.py
pg_db_tools/commands/__init__.py
pg_db_tools/commands/compile.py
pg_db_tools/commands/compile_dot.py
pg_db_tools/commands/compile_md.py
pg_db_tools/commands/compile_rst.py
pg_db_tools/commands/compile_sql.py
pg_db_tools/commands/db_schema.py
pg_db_tools/commands/diff.py
pg_db_tools/commands/doc.py
pg_db_tools/commands/doc_generate.py
pg_db_tools/commands/doc_init.py
pg_db_tools/commands/extract.py
pg_db_tools/commands/extract_from_db.py
pg_db_tools-1.0.7.dist-info/LICENSE
pg_db_tools-1.0.7.dist-info/METADATA
pg_db_tools-1.0.7.dist-info/WHEEL
pg_db_tools-1.0.7.dist-info/entry_points.txt
pg_db_tools-1.0.7.dist-info/top_level.txt
pg_db_tools-1.0.7.dist-info/RECORD
