Metadata-Version: 2.1
Name: pg-db-tools
Version: 1.0.7
Summary: PostgreSQL database schema design and maintenance tools
Home-page: http://www.hendrikx-itc.nl
Author: Alfred Blokland
Author-email: alfred.blokland@hendrikx-itc.nl
License-File: LICENSE
Requires-Dist: PyYAML
Requires-Dist: jsonschema
Requires-Dist: networkx
Requires-Dist: Jinja2
Requires-Dist: psycopg2-binary
